MANIFEST.in
README.txt
setup.cfg
setup.py
collective/__init__.py
collective.referencedatagridfield.egg-info/PKG-INFO
collective.referencedatagridfield.egg-info/SOURCES.txt
collective.referencedatagridfield.egg-info/dependency_links.txt
collective.referencedatagridfield.egg-info/entry_points.txt
collective.referencedatagridfield.egg-info/namespace_packages.txt
collective.referencedatagridfield.egg-info/not-zip-safe
collective.referencedatagridfield.egg-info/requires.txt
collective.referencedatagridfield.egg-info/top_level.txt
collective/referencedatagridfield/__init__.py
collective/referencedatagridfield/_field.py
collective/referencedatagridfield/columns.py
collective/referencedatagridfield/configure.zcml
collective/referencedatagridfield/browser/__init__.py
collective/referencedatagridfield/browser/configure.zcml
collective/referencedatagridfield/browser/datagridref_popup.pt
collective/referencedatagridfield/browser/view.py
collective/referencedatagridfield/examples/ReferenceDataGridDemoType.py
collective/referencedatagridfield/examples/__init__.py
collective/referencedatagridfield/profiles/default/metadata.xml
collective/referencedatagridfield/profiles/default/skins.xml
collective/referencedatagridfield/profiles/examples/factorytool.xml
collective/referencedatagridfield/profiles/examples/metadata.xml
collective/referencedatagridfield/profiles/examples/types.xml
collective/referencedatagridfield/profiles/examples/types/ReferenceDataGridDemoType.xml
collective/referencedatagridfield/skins/referencedatagridfield/datagridwidget_manipulators.pt
collective/referencedatagridfield/skins/referencedatagridfield/referencedatagrid_block_cell.pt
collective/referencedatagridfield/skins/referencedatagridfield/referencedatagrid_hidden_cell.pt
collective/referencedatagridfield/skins/referencedatagridfield/referencedatagrid_styled_cell.pt
collective/referencedatagridfield/skins/referencedatagridfield/referencedatagridwidget.css.dtml
collective/referencedatagridfield/skins/referencedatagridfield/referencedatagridwidget.dev.js
collective/referencedatagridfield/skins/referencedatagridfield/referencedatagridwidget.js
collective/referencedatagridfield/skins/referencedatagridfield/referencedatagridwidget.pt
collective/referencedatagridfield/tests/__init__.py
collective/referencedatagridfield/tests/base.py
collective/referencedatagridfield/tests/testField.py
collective/referencedatagridfield/tests/testInstallation.py
