Metadata-Version: 1.0
Name: collective.referencedatagridfield
Version: 0.5.2
Summary: Mix of Reference and DataGrid Fields
Home-page: https://github.com/collective/collective.referencedatagridfield
Author: Quintagroup
Author-email: support@quintagroup.com
License: GPL
Keywords: archetypes referencebrowser datagrid field widget relation
Platform: UNKNOWN
Classifier: Framework :: Plone
Classifier: Programming Language :: Python
Classifier: Topic :: Software Development :: Libraries :: Python Modules
Classifier: License :: OSI Approved :: GNU General Public License (GPL)
